{
  "timestamp": "2026-01-23T17:20:09.010003+00:00",
  "config": {
    "epochs": 20,
    "lr": 0.001,
    "weight_decay": 0.0001,
    "optimizer": "adam",
    "momentum": 0.9,
    "seed": 42,
    "device": null,
    "checkpoint_path": "models/resnet18_eurosat4.pt",
    "log_dir": "outputs/runs",
    "data": {
      "data_dir": "data/raw",
      "batch_size": 32,
      "sample_every": 40,
      "num_workers": 4,
      "pin_memory": true
    },
    "model": {
      "model_name": "resnet18.a1_in1k",
      "num_classes": 10,
      "pretrained": true,
      "freeze_backbone": true
    },
    "enable_profiling": false,
    "enable_wandb": true,
    "wandb_entity": "mlopstesting",
    "wandb_project": "s_kruh_te"
  },
  "history": [
    {
      "epoch": 1,
      "train_loss": 2.2251713116963705,
      "train_acc": 0.1685185185185185,
      "val_loss": 2.1183509826660156,
      "val_acc": 0.3382352941176471
    },
    {
      "epoch": 2,
      "train_loss": 2.0030624363157483,
      "train_acc": 0.40370370370370373,
      "val_loss": 1.8912036278668571,
      "val_acc": 0.6029411764705882
    },
    {
      "epoch": 3,
      "train_loss": 1.8363708231184217,
      "train_acc": 0.562962962962963,
      "val_loss": 1.71933711977566,
      "val_acc": 0.6617647058823529
    },
    {
      "epoch": 4,
      "train_loss": 1.6836954063839382,
      "train_acc": 0.6222222222222222,
      "val_loss": 1.584790874929989,
      "val_acc": 0.6470588235294118
    },
    {
      "epoch": 5,
      "train_loss": 1.578441361144737,
      "train_acc": 0.6425925925925926,
      "val_loss": 1.478987083715551,
      "val_acc": 0.6470588235294118
    },
    {
      "epoch": 6,
      "train_loss": 1.48037258165854,
      "train_acc": 0.662962962962963,
      "val_loss": 1.3844625879736507,
      "val_acc": 0.6617647058823529
    },
    {
      "epoch": 7,
      "train_loss": 1.4171021426165546,
      "train_acc": 0.6851851851851852,
      "val_loss": 1.3129732678918278,
      "val_acc": 0.6764705882352942
    },
    {
      "epoch": 8,
      "train_loss": 1.318397773636712,
      "train_acc": 0.7388888888888889,
      "val_loss": 1.2572736179127413,
      "val_acc": 0.6911764705882353
    },
    {
      "epoch": 9,
      "train_loss": 1.245586955105817,
      "train_acc": 0.7203703703703703,
      "val_loss": 1.1856658388586605,
      "val_acc": 0.6911764705882353
    },
    {
      "epoch": 10,
      "train_loss": 1.2417569151631107,
      "train_acc": 0.7185185185185186,
      "val_loss": 1.1303317441659815,
      "val_acc": 0.7205882352941176
    },
    {
      "epoch": 11,
      "train_loss": 1.138888919795001,
      "train_acc": 0.7444444444444445,
      "val_loss": 1.087968142593608,
      "val_acc": 0.7205882352941176
    },
    {
      "epoch": 12,
      "train_loss": 1.129265879701685,
      "train_acc": 0.7296296296296296,
      "val_loss": 1.0668937949573292,
      "val_acc": 0.7205882352941176
    },
    {
      "epoch": 13,
      "train_loss": 1.0838786928742021,
      "train_acc": 0.7314814814814815,
      "val_loss": 1.024133910151089,
      "val_acc": 0.7205882352941176
    },
    {
      "epoch": 14,
      "train_loss": 1.055500449957671,
      "train_acc": 0.7462962962962963,
      "val_loss": 1.0104038820547216,
      "val_acc": 0.7058823529411765
    },
    {
      "epoch": 15,
      "train_loss": 1.01315502193239,
      "train_acc": 0.7462962962962963,
      "val_loss": 0.9639869121944203,
      "val_acc": 0.7352941176470589
    },
    {
      "epoch": 16,
      "train_loss": 1.023162970277998,
      "train_acc": 0.7296296296296296,
      "val_loss": 0.9358914178960464,
      "val_acc": 0.7352941176470589
    },
    {
      "epoch": 17,
      "train_loss": 0.9854275014665391,
      "train_acc": 0.7314814814814815,
      "val_loss": 0.9339757000698763,
      "val_acc": 0.7205882352941176
    },
    {
      "epoch": 18,
      "train_loss": 0.9859685632917616,
      "train_acc": 0.7685185185185185,
      "val_loss": 0.8982569084447973,
      "val_acc": 0.75
    },
    {
      "epoch": 19,
      "train_loss": 0.9498462504810757,
      "train_acc": 0.737037037037037,
      "val_loss": 0.8895634658196393,
      "val_acc": 0.7352941176470589
    },
    {
      "epoch": 20,
      "train_loss": 0.9443687112243088,
      "train_acc": 0.737037037037037,
      "val_loss": 0.8704818662475137,
      "val_acc": 0.7647058823529411
    }
  ]
}